Metadata-Version: 1.0
Name: beowulf
Version: 0.1
Summary: Ironclad, miscellaneous utilities.
Home-page: https://github.com/second-breakfast/beowulf
Author: Peregrin Took
Author-email: peregrin.took@example.com
License: MIT
Platform: UNKNOWN
